__init__.py
pride_checksum/__init__.py
pride_checksum/__main__.py
pride_checksum-1.2.0.dist-info/METADATA
pride_checksum-1.2.0.dist-info/WHEEL
pride_checksum-1.2.0.dist-info/entry_points.txt
pride_checksum-1.2.0.dist-info/top_level.txt
pride_checksum-1.2.0.dist-info/RECORD
