Metadata-Version: 2.4
Name: pride-checksum
Version: 1.2.0
Summary: Computes SHA-1 checksum for all the specified files  and writes to checksum.txt file.
Author-email: PRIDE Archive <pride-support@ebi.ac.uk>
License: MIT
Project-URL: Homepage, https://github.com/PRIDE-Archive/pride-checksum
Project-URL: Bug Tracker, https://github.com/PRIDE-Archive/pride-checksum/issues
Keywords: checksum,sha1,validation,bioinformatics
Classifier: Development Status :: 5 - Production/Stable
Classifier: Intended Audience :: Science/Research
Classifier: License :: OSI Approved :: MIT License
Classifier: Operating System :: OS Independent
Classifier: Programming Language :: Python :: 3
Classifier: Programming Language :: Python :: 3.11
Classifier: Programming Language :: Python :: 3.12
Classifier: Topic :: Scientific/Engineering :: Bio-Informatics
Classifier: Topic :: Security :: Cryptography
Requires-Python: >=3.11
Requires-Dist: click
Provides-Extra: dev
Requires-Dist: pytest; extra == "dev"
Requires-Dist: pytest-cov; extra == "dev"
